<rec>

<itemid>uni-ucl-jud-0130588-001</itemid>

<subscription>
	<unit>unpublished</unit>
	<country>uni</country>
</subscription>

<itemimagefiles>
<itemimage>
	<itemimagefile1>uni-ucl-jud-0130588-001-0001R</itemimagefile1><order>1</order><imagenumber>1</imagenumber><colour>monochrome</colour><pagetype>Title page</pagetype>
</itemimage>
<itemimage>
	<itemimagefile1>uni-ucl-jud-0130588-001-0002L</itemimagefile1><order>2</order><imagenumber>2</imagenumber><colour>monochrome</colour><pagecontent number="1">Manuscript (i.e. handwritten) marginalia and other annotation</pagecontent><pagetype>None</pagetype>
</itemimage>
<itemimage>
	<itemimagefile1>uni-ucl-jud-0130588-001-0003R</itemimagefile1><order>3</order><imagenumber>3</imagenumber><orderlabel>1|A 2</orderlabel><colour>monochrome</colour><pagecontent number="1">Illuminated lettering</pagecontent><pagetype>None</pagetype>
</itemimage>
<itemimage>
	<itemimagefile1>uni-ucl-jud-0130588-001-0004L</itemimagefile1><order>4</order><imagenumber>4</imagenumber><orderlabel>2</orderlabel><colour>monochrome</colour><pagetype>None</pagetype>
</itemimage>
<itemimage>
	<itemimagefile1>uni-ucl-jud-0130588-001-0005R</itemimagefile1><order>5</order><imagenumber>5</imagenumber><orderlabel>3</orderlabel><colour>monochrome</colour><pagetype>None</pagetype>
</itemimage>
<itemimage>
	<itemimagefile1>uni-ucl-jud-0130588-001-0006L</itemimagefile1><order>6</order><imagenumber>6</imagenumber><orderlabel>4</orderlabel><colour>monochrome</colour><pagetype>None</pagetype>
</itemimage>
<itemimage>
	<itemimagefile1>uni-ucl-jud-0130588-001-0007R</itemimagefile1><order>7</order><imagenumber>7</imagenumber><orderlabel>5</orderlabel><colour>monochrome</colour><pagetype>None</pagetype>
</itemimage>
<itemimage>
	<itemimagefile1>uni-ucl-jud-0130588-001-0008L</itemimagefile1><order>8</order><imagenumber>8</imagenumber><orderlabel>6</orderlabel><colour>monochrome</colour><pagetype>None</pagetype>
</itemimage>
<itemimage>
	<itemimagefile1>uni-ucl-jud-0130588-001-0009R</itemimagefile1><order>9</order><imagenumber>9</imagenumber><orderlabel>7|B </orderlabel><colour>monochrome</colour><pagetype>None</pagetype>
</itemimage>
<itemimage>
	<itemimagefile1>uni-ucl-jud-0130588-001-0010L</itemimagefile1><order>10</order><imagenumber>10</imagenumber><orderlabel>8</orderlabel><colour>monochrome</colour><pagetype>None</pagetype>
</itemimage>
<itemimage>
	<itemimagefile1>uni-ucl-jud-0130588-001-0011R</itemimagefile1><order>11</order><imagenumber>11</imagenumber><orderlabel>9|B 2</orderlabel><colour>monochrome</colour><pagetype>None</pagetype>
</itemimage>
<itemimage>
	<itemimagefile1>uni-ucl-jud-0130588-001-0012L</itemimagefile1><order>12</order><imagenumber>12</imagenumber><orderlabel>10</orderlabel><colour>monochrome</colour><pagetype>None</pagetype>
</itemimage>
<itemimage>
	<itemimagefile1>uni-ucl-jud-0130588-001-0013R</itemimagefile1><order>13</order><imagenumber>13</imagenumber><orderlabel>11</orderlabel><colour>monochrome</colour><pagetype>None</pagetype>
</itemimage>
<itemimage>
	<itemimagefile1>uni-ucl-jud-0130588-001-0014L</itemimagefile1><order>14</order><imagenumber>14</imagenumber><orderlabel>12|*</orderlabel><colour>monochrome</colour><pagetype>None</pagetype>
</itemimage>
<itemimage>
	<itemimagefile1>uni-ucl-jud-0130588-001-0015R</itemimagefile1><order>15</order><imagenumber>15</imagenumber><orderlabel>13</orderlabel><colour>monochrome</colour><pagetype>None</pagetype>
</itemimage>
<itemimage>
	<itemimagefile1>uni-ucl-jud-0130588-001-0016L</itemimagefile1><order>16</order><imagenumber>16</imagenumber><orderlabel>14</orderlabel><colour>monochrome</colour><pagetype>None</pagetype>
</itemimage>
<itemimage>
	<itemimagefile1>uni-ucl-jud-0130588-001-0017R</itemimagefile1><order>17</order><imagenumber>17</imagenumber><orderlabel>15|C </orderlabel><colour>monochrome</colour><pagetype>None</pagetype>
</itemimage>
<itemimage>
	<itemimagefile1>uni-ucl-jud-0130588-001-0018L</itemimagefile1><order>18</order><imagenumber>18</imagenumber><orderlabel>16</orderlabel><colour>monochrome</colour><pagetype>None</pagetype>
</itemimage>
<itemimage>
	<itemimagefile1>uni-ucl-jud-0130588-001-0019R</itemimagefile1><order>19</order><imagenumber>19</imagenumber><orderlabel>17|C 2</orderlabel><colour>monochrome</colour><pagetype>None</pagetype>
</itemimage>
<itemimage>
	<itemimagefile1>uni-ucl-jud-0130588-001-0020L</itemimagefile1><order>20</order><imagenumber>20</imagenumber><orderlabel>18|*</orderlabel><colour>monochrome</colour><pagetype>None</pagetype>
</itemimage>
<itemimage>
	<itemimagefile1>uni-ucl-jud-0130588-001-0021R</itemimagefile1><order>21</order><imagenumber>21</imagenumber><orderlabel>19</orderlabel><colour>monochrome</colour><pagetype>None</pagetype>
</itemimage>
<itemimage>
	<itemimagefile1>uni-ucl-jud-0130588-001-0022L</itemimagefile1><order>22</order><imagenumber>22</imagenumber><orderlabel>20</orderlabel><colour>monochrome</colour><pagetype>None</pagetype>
</itemimage>
<itemimage>
	<itemimagefile1>uni-ucl-jud-0130588-001-0023R</itemimagefile1><order>23</order><imagenumber>23</imagenumber><orderlabel>21</orderlabel><colour>monochrome</colour><pagetype>None</pagetype>
</itemimage>
<itemimage>
	<itemimagefile1>uni-ucl-jud-0130588-001-0024L</itemimagefile1><order>24</order><imagenumber>24</imagenumber><orderlabel>22</orderlabel><colour>monochrome</colour><pagetype>None</pagetype>
</itemimage>
<itemimage>
	<itemimagefile1>uni-ucl-jud-0130588-001-0025R</itemimagefile1><order>25</order><imagenumber>25</imagenumber><orderlabel>23|D</orderlabel><colour>monochrome</colour><pagetype>None</pagetype>
</itemimage>
<itemimage>
	<itemimagefile1>uni-ucl-jud-0130588-001-0026L</itemimagefile1><order>26</order><imagenumber>26</imagenumber><orderlabel>24</orderlabel><colour>monochrome</colour><pagetype>None</pagetype>
</itemimage>
<itemimage>
	<itemimagefile1>uni-ucl-jud-0130588-001-0027R</itemimagefile1><order>27</order><imagenumber>27</imagenumber><orderlabel>25|D 2</orderlabel><colour>monochrome</colour><pagetype>None</pagetype>
</itemimage>
<itemimage>
	<itemimagefile1>uni-ucl-jud-0130588-001-0028L</itemimagefile1><order>28</order><imagenumber>28</imagenumber><orderlabel>26|*</orderlabel><colour>monochrome</colour><pagetype>None</pagetype>
</itemimage>
<itemimage>
	<itemimagefile1>uni-ucl-jud-0130588-001-0029R</itemimagefile1><order>29</order><imagenumber>29</imagenumber><orderlabel>27</orderlabel><colour>monochrome</colour><pagetype>None</pagetype>
</itemimage>
<itemimage>
	<itemimagefile1>uni-ucl-jud-0130588-001-0030L</itemimagefile1><order>30</order><imagenumber>30</imagenumber><orderlabel>28</orderlabel><colour>monochrome</colour><pagetype>None</pagetype>
</itemimage>
<itemimage>
	<itemimagefile1>uni-ucl-jud-0130588-001-0031R</itemimagefile1><order>31</order><imagenumber>31</imagenumber><orderlabel>29</orderlabel><colour>monochrome</colour><pagetype>None</pagetype>
</itemimage>
<itemimage>
	<itemimagefile1>uni-ucl-jud-0130588-001-0032L</itemimagefile1><order>32</order><imagenumber>32</imagenumber><orderlabel>30</orderlabel><colour>monochrome</colour><pagetype>None</pagetype>
</itemimage>
<itemimage>
	<itemimagefile1>uni-ucl-jud-0130588-001-0033R</itemimagefile1><order>33</order><imagenumber>33</imagenumber><orderlabel>31|E </orderlabel><colour>monochrome</colour><pagetype>None</pagetype>
</itemimage>
<itemimage>
	<itemimagefile1>uni-ucl-jud-0130588-001-0034L</itemimagefile1><order>34</order><imagenumber>34</imagenumber><orderlabel>32</orderlabel><colour>monochrome</colour><pagetype>None</pagetype>
</itemimage>
<itemimage>
	<itemimagefile1>uni-ucl-jud-0130588-001-0035R</itemimagefile1><order>35</order><imagenumber>35</imagenumber><orderlabel>33|E 2</orderlabel><colour>monochrome</colour><pagetype>None</pagetype>
</itemimage>
<itemimage>
	<itemimagefile1>uni-ucl-jud-0130588-001-0036L</itemimagefile1><order>36</order><imagenumber>36</imagenumber><orderlabel>34</orderlabel><colour>monochrome</colour><pagetype>None</pagetype>
</itemimage>
<itemimage>
	<itemimagefile1>uni-ucl-jud-0130588-001-0037R</itemimagefile1><order>37</order><imagenumber>37</imagenumber><orderlabel>35</orderlabel><colour>monochrome</colour><pagetype>None</pagetype>
</itemimage>
<itemimage>
	<itemimagefile1>uni-ucl-jud-0130588-001-0038L</itemimagefile1><order>38</order><imagenumber>38</imagenumber><orderlabel>36</orderlabel><colour>monochrome</colour><pagetype>None</pagetype>
</itemimage>
<itemimage>
	<itemimagefile1>uni-ucl-jud-0130588-001-0039R</itemimagefile1><order>39</order><imagenumber>39</imagenumber><orderlabel>37|*</orderlabel><colour>monochrome</colour><pagetype>None</pagetype>
</itemimage>
<itemimage>
	<itemimagefile1>uni-ucl-jud-0130588-001-0040L</itemimagefile1><order>40</order><imagenumber>40</imagenumber><orderlabel>38</orderlabel><colour>monochrome</colour><pagetype>None</pagetype>
</itemimage>
<itemimage>
	<itemimagefile1>uni-ucl-jud-0130588-001-0041R</itemimagefile1><order>41</order><imagenumber>41</imagenumber><orderlabel>39|F </orderlabel><colour>monochrome</colour><pagetype>None</pagetype>
</itemimage>
<itemimage>
	<itemimagefile1>uni-ucl-jud-0130588-001-0042L</itemimagefile1><order>42</order><imagenumber>42</imagenumber><orderlabel>40</orderlabel><colour>monochrome</colour><pagetype>None</pagetype>
</itemimage>
</itemimagefiles>

<rec_search>
<pqid>uni-ucl-jud-0130588-001</pqid>
<title>A conference betwixt a Protestant and a Jevv: or, A second letter from a merchant in London, to his correspondent in Amsterdam.</title>
<author_main>
	<author_name>Richard Mayo</author_name>
	<author_corrected>Mayo, Richard, 1631?-1695.</author_corrected>
	<author_uninverted>Richard, Mayo, 1631?-1695.</author_uninverted>
</author_main>
<startdate>16780101</startdate>
<enddate>16781231</enddate>
<displaydate>1678</displaydate>
<imprint>London: Tho. Parkhurst, 1678.</imprint>
<shelfmark>STRONG ROOM MOCATTA 1678 M1</shelfmark>
<publisher_printer>Tho. Parkhurst</publisher_printer>
<place_of_publication>London</place_of_publication>
<country_of_publication>England</country_of_publication>
<pagination>[2], 40, [2] p ; 20 cm.</pagination>
<source_library>University College London</source_library>
<source_collection>Special Collections, UCL Library</source_collection>
<language>English</language>
<illustrations>
	<illustration>Manuscript (i.e. handwritten) marginalia and other annotation</illustration>
	<illustration>Illuminated lettering</illustration>
</illustrations>

</rec_search>


</rec>